{
  "categoryName": "Послуги",
  "categoryDescription": "Умовні послуги з налаштування, діагностики та підтримки техніки.",
  "items": [
    {
      "id": 1,
      "name": "Налаштування ноутбука",
      "shortname": "laptopsetup",
      "description": "Встановлення базових програм, налаштування системи та перевірка роботи.",
      "price": 700
    },
    {
      "id": 2,
      "name": "Чистка системи",
      "shortname": "systemcleaning",
      "description": "Очищення тимчасових файлів, перевірка автозавантаження та оптимізація.",
      "price": 500
    },
    {
      "id": 3,
      "name": "Консультація",
      "shortname": "consultation",
      "description": "Допомога з вибором техніки або пояснення роботи програмного забезпечення.",
      "price": 300
    },
    {
      "id": 4,
      "name": "Резервне копіювання",
      "shortname": "backup",
      "description": "Створення копії важливих файлів на зовнішній носій або хмарне сховище.",
      "price": 600
    },
    {
      "id": 5,
      "name": "Встановлення ПЗ",
      "shortname": "softwareinstall",
      "description": "Встановлення та базове налаштування потрібних користувачу програм.",
      "price": 450
    }
  ]
}
